{
  "arxiv_2303_01037": [],
  "arxiv_2303_01664": [],
  "arxiv_2405_19487": [],
  "arxiv_2406_02430": [],
  "arxiv_2502_14145": [],
  "arxiv_2504_08528": [
    "arxiv_2303_01037",
    "arxiv_2405_19487"
  ],
  "arxiv_2505_04457": [
    null
  ],
  "arxiv_2505_17060": [],
  "arxiv_2510_03597": [],
  "arxiv_2602_01914": [],
  "arxiv_2602_06053": [],
  "arxiv_2603_14877": [],
  "arxiv_2603_25750": [
    "arxiv_2602_06053",
    "arxiv_2405_19487"
  ],
  "arxiv_2604_04847": [],
  "arxiv_2604_09344": [],
  "arxiv_2605_19833": [],
  "arxiv_2605_21008": [],
  "arxiv_2605_22083": [],
  "arxiv_2605_22170": [],
  "arxiv_2605_27258": [],
  "arxiv_2605_28063": [],
  "arxiv_2605_30748": [],
  "arxiv_2605_30965": [],
  "arxiv_2605_30993": [],
  "arxiv_2605_31173": [],
  "arxiv_2605_31521": [],
  "arxiv_2605_31530": [
    "arxiv_2406_02430"
  ],
  "microsoft_mai_thinking_1": [],
  "paper_1780385949770": []
}
